{
  "agent": {
    "metrics_collection_interval": 60,
    "run_as_user": "root"
  },
  "metrics": {
    "namespace": "Routie/EC2",
    "metrics_collected": {
      "cpu": {
        "measurement": [
          {
            "name": "cpu_usage_idle",
            "rename": "CPU_IDLE",
            "unit": "Percent"
          },
          {
            "name": "cpu_usage_iowait",
            "rename": "CPU_IOWAIT",
            "unit": "Percent"
          },
          "cpu_time_guest"
        ],
        "metrics_collection_interval": 60,
        "resources": [
          "*"
        ],
        "totalcpu": false
      },
      "disk": {
        "measurement": [
          {
            "name": "used_percent",
            "rename": "DISK_USED",
            "unit": "Percent"
          },
          "inodes_free"
        ],
        "metrics_collection_interval": 60,
        "resources": [
          "*"
        ]
      },
      "diskio": {
        "measurement": [
          "io_time",
          "write_bytes",
          "read_bytes",
          "writes",
          "reads"
        ],
        "metrics_collection_interval": 60,
        "resources": [
          "*"
        ]
      },
      "mem": {
        "measurement": [
          {
            "name": "mem_used_percent",
            "rename": "MEM_USED",
            "unit": "Percent"
          }
        ],
        "metrics_collection_interval": 60
      },
      "netstat": {
        "measurement": [
          "tcp_established",
          "tcp_time_wait"
        ],
        "metrics_collection_interval": 60
      },
      "swap": {
        "measurement": [
          {
            "name": "swap_used_percent",
            "rename": "SWAP_USED",
            "unit": "Percent"
          }
        ],
        "metrics_collection_interval": 60
      }
    }
  },
  "logs": {
    "logs_collected": {
      "files": {
        "collect_list": [
          {
            "file_path": "/var/log/syslog",
            "log_group_name": "/aws/ec2/routie/syslog",
            "log_stream_name": "{instance_id}",
            "timezone": "UTC"
          },
          {
            "file_path": "/var/log/nginx/access.log",
            "log_group_name": "/aws/ec2/routie/nginx/access",
            "log_stream_name": "{instance_id}",
            "timezone": "UTC"
          },
          {
            "file_path": "/var/log/nginx/error.log",
            "log_group_name": "/aws/ec2/routie/nginx/error",
            "log_stream_name": "{instance_id}",
            "timezone": "UTC"
          },
          {
            "file_path": "/home/ubuntu/logs/routie.log",
            "log_group_name": "/aws/ec2/routie/application",
            "log_stream_name": "{instance_id}",
            "timezone": "Asia/Seoul"
          },
          {
            "file_path": "/home/ubuntu/logs/routie-exception.json",
            "log_group_name": "/aws/ec2/routie/exception",
            "log_stream_name": "{instance_id}",
            "timezone": "Asia/Seoul"
          },
          {
            "file_path": "/home/ubuntu/logs/routie-request.json",
            "log_group_name": "/aws/ec2/routie/request",
            "log_stream_name": "{instance_id}",
            "timezone": "Asia/Seoul"
          }
        ]
      }
    }
  }
}

